dcargs/__init__.py
dcargs/_argparse_formatter.py
dcargs/_arguments.py
dcargs/_calling.py
dcargs/_cli.py
dcargs/_deprecated.py
dcargs/_docstrings.py
dcargs/_fields.py
dcargs/_instantiators.py
dcargs/_parsers.py
dcargs/_resolver.py
dcargs/_shtab/LICENCE
dcargs/_shtab/README.md
dcargs/_shtab/__init__.py
dcargs/_shtab/__main__.py
dcargs/_shtab/_dist_ver.py
dcargs/_shtab/main.py
dcargs/_shtab/py.typed
dcargs/_singleton.py
dcargs/_strings.py
dcargs/conf/__init__.py
dcargs/conf/_markers.py
dcargs/conf/_subcommands.py
dcargs/extras/__init__.py
dcargs/extras/_base_configs.py
dcargs/extras/_choices_type.py
dcargs/extras/_serialization.py
dcargs/py.typed
dcargs-0.3.22.dist-info/LICENSE
dcargs-0.3.22.dist-info/WHEEL
dcargs-0.3.22.dist-info/METADATA
dcargs-0.3.22.dist-info/RECORD
