Metadata-Version: 2.1
Name: dcargs
Version: 0.3.22
Summary: Deprecated! Install tyro instead
Home-page: https://github.com/brentyi/dcargs
Author: brentyi
Author-email: brentyi@berkeley.edu
Requires-Python: >=3.7,<4.0
Classifier: Programming Language :: Python :: 3
Classifier: Programming Language :: Python :: 3.7
Classifier: Programming Language :: Python :: 3.8
Classifier: Programming Language :: Python :: 3.9
Classifier: Programming Language :: Python :: 3.10
Requires-Dist: PyYAML (>=6.0,<7.0)
Requires-Dist: backports.cached-property (>=1.0.2,<2.0.0); python_version >= "3.7" and python_version < "3.8"
Requires-Dist: colorama (>=0.4.0,<0.5.0); sys_platform == "win32"
Requires-Dist: docstring-parser (>=0.14.1,<0.15.0)
Requires-Dist: frozendict (>=2.3.4,<3.0.0)
Requires-Dist: rich (>=11.1.0)
Requires-Dist: typing-extensions (>=4.3.0,<5.0.0)
Project-URL: Documentation, https://brentyi.github.io/dcargs/
Project-URL: Repository, https://github.com/brentyi/dcargs
